NIDRA/__init__.py
NIDRA/forehead_scorer.py
NIDRA/plotting.py
NIDRA/psg_scorer.py
NIDRA/utils.py
NIDRA/nidra_gui/__init__.py
NIDRA/nidra_gui/app.py
NIDRA/nidra_gui/launcher.py
NIDRA/nidra_gui/neutralino/resources/logo.png
NIDRA/nidra_gui/neutralino/resources/icons/appIcon.png
NIDRA/nidra_gui/neutralino/resources/icons/logo.gif
NIDRA/nidra_gui/neutralino/resources/icons/trayIcon.png
NIDRA/nidra_gui/neutralino/resources/js/neutralino.d.ts
NIDRA/nidra_gui/neutralino/resources/js/neutralino.js
NIDRA/nidra_gui/neutralino/resources/static/script.js
NIDRA/nidra_gui/neutralino/resources/static/style.css
NIDRA/nidra_gui/neutralino/resources/templates/index.html
docs/__init__.py
docs/_redirects
docs/dashboard.png
docs/gui.png
docs/logo.ico
docs/logo.png
docs/logo_small.png
docs/manual.html
docs/matrix.png
docs/style.css
nidra-0.2.3.dist-info/licenses/LICENSE
nidra-0.2.3.dist-info/METADATA
nidra-0.2.3.dist-info/WHEEL
nidra-0.2.3.dist-info/entry_points.txt
nidra-0.2.3.dist-info/top_level.txt
nidra-0.2.3.dist-info/RECORD
