Metadata-Version: 2.4
Name: NIDRA
Version: 0.2.3
Summary: A tool for scoring sleep data from PSG and forehead EEG recordings.
Author-email: pzerr <zerr.paul@gmail.com>
License-Expression: MIT
Project-URL: Homepage, https://github.com/paulzerr/NIDRA
Classifier: Programming Language :: Python :: 3
Classifier: Operating System :: OS Independent
Requires-Python: >=3.9
License-File: LICENSE
Requires-Dist: scipy
Requires-Dist: mne
Requires-Dist: seaborn
Requires-Dist: pandas
Requires-Dist: matplotlib
Requires-Dist: Flask
Requires-Dist: huggingface_hub
Requires-Dist: hf_xet
Requires-Dist: pydantic-core==2.33.0
Requires-Dist: appdirs
Requires-Dist: requests
Requires-Dist: pywebview
Requires-Dist: psutil
Requires-Dist: numpy>=2.0.0
Requires-Dist: onnxruntime>=1.19.0
Dynamic: license-file
Dynamic: requires-dist
